AttentionMOI/__init__.py
AttentionMOI/deepmoi.py
AttentionMOI/src/__init__.py
AttentionMOI/src/explain.py
AttentionMOI/src/feature_selection.py
AttentionMOI/src/fsd.py
AttentionMOI/src/main.py
AttentionMOI/src/module.py
AttentionMOI/src/prediction.py
AttentionMOI/src/preprocess.py
AttentionMOI/src/train.py
AttentionMOI/src/utils.py
AttentionMOI/src/moanna/__init__.py
AttentionMOI/src/moanna/__meta__.py
AttentionMOI/src/moanna/cli.py
AttentionMOI/src/moanna/main.py
AttentionMOI/src/moanna/helper/ClusteringMetricsHelper.py
AttentionMOI/src/moanna/helper/DataCleanUpFunctions.py
AttentionMOI/src/moanna/helper/SurvivalHelperFunctions.py
AttentionMOI/src/moanna/helper/__init__.py
AttentionMOI/src/moanna/model/Autoencoder.py
AttentionMOI/src/moanna/model/ClassificationModel.py
AttentionMOI/src/moanna/model/Moanna.py
AttentionMOI/src/moanna/model/__init__.py
AttentionMOI/src/mogonet/__init__.py
AttentionMOI/src/mogonet/feat_importance.py
AttentionMOI/src/mogonet/main_biomarker.py
AttentionMOI/src/mogonet/main_mogonet.py
AttentionMOI/src/mogonet/models.py
AttentionMOI/src/mogonet/train_test.py
AttentionMOI/src/mogonet/utils.py
AttentionMOI-0.0.7.data/data/cnv.csv.gz
AttentionMOI-0.0.7.data/data/label.csv
AttentionMOI-0.0.7.data/data/met.csv.gz
AttentionMOI-0.0.7.data/data/rna.csv.gz
AttentionMOI-0.0.7.dist-info/LICENSE
AttentionMOI-0.0.7.dist-info/METADATA
AttentionMOI-0.0.7.dist-info/WHEEL
AttentionMOI-0.0.7.dist-info/dependency_links.txt
AttentionMOI-0.0.7.dist-info/entry_points.txt
AttentionMOI-0.0.7.dist-info/top_level.txt
AttentionMOI-0.0.7.dist-info/RECORD
